gcfit/__init__.py
gcfit/analysis/__init__.py
gcfit/analysis/models.py
gcfit/analysis/runs.py
gcfit/core/__init__.py
gcfit/core/data.py
gcfit/core/main.py
gcfit/probabilities/__init__.py
gcfit/probabilities/priors.py
gcfit/probabilities/probabilities.py
gcfit/probabilities/pulsars.py
gcfit/resources/NGC0104.hdf
gcfit/resources/NGC0288.hdf
gcfit/resources/NGC0362.hdf
gcfit/resources/NGC1261.hdf
gcfit/resources/NGC1851.hdf
gcfit/resources/NGC2808.hdf
gcfit/resources/NGC3201.hdf
gcfit/resources/NGC4372.hdf
gcfit/resources/NGC4590.hdf
gcfit/resources/NGC4833.hdf
gcfit/resources/NGC5024.hdf
gcfit/resources/NGC5139.hdf
gcfit/resources/NGC5272.hdf
gcfit/resources/NGC5904.hdf
gcfit/resources/NGC5927.hdf
gcfit/resources/NGC5986.hdf
gcfit/resources/NGC6093.hdf
gcfit/resources/NGC6121.hdf
gcfit/resources/NGC6171.hdf
gcfit/resources/NGC6205.hdf
gcfit/resources/NGC6218.hdf
gcfit/resources/NGC6254.hdf
gcfit/resources/NGC6266.hdf
gcfit/resources/NGC6341.hdf
gcfit/resources/NGC6352.hdf
gcfit/resources/NGC6362.hdf
gcfit/resources/NGC6366.hdf
gcfit/resources/NGC6397.hdf
gcfit/resources/NGC6541.hdf
gcfit/resources/NGC6624.hdf
gcfit/resources/NGC6656.hdf
gcfit/resources/NGC6681.hdf
gcfit/resources/NGC6723.hdf
gcfit/resources/NGC6752.hdf
gcfit/resources/NGC6779.hdf
gcfit/resources/NGC6809.hdf
gcfit/resources/NGC6981.hdf
gcfit/resources/NGC7078.hdf
gcfit/resources/NGC7089.hdf
gcfit/resources/NGC7099.hdf
gcfit/resources/TEST.hdf
gcfit/resources/field_msp.dat
gcfit/resources/specification.json
gcfit/scripts/GCfitter.py
gcfit/scripts/__init__.py
gcfit/scripts/generate_model_CI.py
gcfit/util/__init__.py
gcfit/util/data.py
gcfit/util/mass.py
gcfit/util/probabilities.py
gcfit/util/units.py
gcfit-2.0.dist-info/METADATA
gcfit-2.0.dist-info/WHEEL
gcfit-2.0.dist-info/entry_points.txt
gcfit-2.0.dist-info/licenses/LICENSE
gcfit-2.0.dist-info/RECORD
