Metadata-Version: 2.3
Name: GCfit
Version: 2.0
Summary: Fitting of multimass equilibrium models of globular clusters
Project-URL: documentation, https://gcfit.readthedocs.io
Project-URL: repository, https://github.com/nmdickson/GCfit.git
Author-email: Nolan Dickson <nolan.dickson@smu.ca>, Peter Smith <smith.peter.902@gmail.com>, Vincent Henault-Brunet <Vincent.Henault@smu.ca>
License: MIT License
License-File: LICENSE
Keywords: GCfit,Globular Cluster,Star Cluster
Classifier: Development Status :: 5 - Production/Stable
Classifier: Intended Audience :: Science/Research
Classifier: License :: OSI Approved :: MIT License
Classifier: Programming Language :: Python
Classifier: Topic :: Scientific/Engineering :: Astronomy
Requires-Python: >=3.9
Requires-Dist: ads
Requires-Dist: astro-limepy
Requires-Dist: astro-ssptools
Requires-Dist: astropy
Requires-Dist: corner
Requires-Dist: dynesty
Requires-Dist: emcee
Requires-Dist: gala
Requires-Dist: h5py
Requires-Dist: matplotlib
Requires-Dist: numpy
Requires-Dist: schwimmbad
Requires-Dist: scipy
Requires-Dist: shapely
Requires-Dist: sphinx-toggleprompt
Requires-Dist: tqdm
Provides-Extra: test
Requires-Dist: pytest; extra == 'test'
